{
  "actions": [
    {
      "acted_at": "2014-05-09T10:52:00-04:00", 
      "references": [
        {
          "reference": "CR H4037-4038, H4042-4043", 
          "type": "consideration"
        }, 
        {
          "reference": "CR H4037", 
          "type": "text"
        }
      ], 
      "text": "Amendment (A008) offered by Ms. Wilson (FL).", 
      "type": "action"
    }, 
    {
      "acted_at": "2014-05-09T11:58:00-04:00", 
      "how": "roll", 
      "references": [], 
      "result": "pass", 
      "roll": 214, 
      "text": "On agreeing to the Wilson (FL) amendment (A008) Agreed to by recorded vote: 373 - 32 (Roll no. 214).", 
      "type": "vote", 
      "vote_type": "vote", 
      "where": "h"
    }
  ], 
  "amendment_id": "hamdt660-113", 
  "amendment_type": "hamdt", 
  "amends_amendment": null, 
  "amends_bill": {
    "bill_id": "hr10-113", 
    "bill_type": "hr", 
    "congress": 113, 
    "number": 10
  }, 
  "amends_treaty": null, 
  "chamber": "h", 
  "congress": "113", 
  "description": "Amendment provides for the collection and public dissemination of information by charter schools on demographics, quality of education, school attendance, average class size, academic achievement gains, parental involvement and discipline.", 
  "house_number": 8, 
  "introduced_at": "2014-05-09", 
  "number": 660, 
  "purpose": "An amendment numbered 9 printed in House Report 113-444 to ensure collection and public dissemination of information that will help parents make informed decisions about education options for their children.", 
  "sponsor": {
    "district": "24", 
    "name": "Wilson, Frederica S.", 
    "state": "FL", 
    "thomas_id": "02004", 
    "title": "Rep", 
    "type": "person"
  }, 
  "status": "pass", 
  "status_at": "2014-05-09T11:58:00-04:00", 
  "updated_at": "2014-08-14T13:37:02-04:00"
}