<bill session="113" type="hj" number="20" updated="2014-08-18T01:50:08-04:00">
  <state datetime="2013-01-22">REFERRED</state>
  <status>
    <introduced datetime="2013-01-22"/>
  </status>
  <introduced datetime="2013-01-22"/>
  <titles>
    <title type="official" as="introduced">Proposing an amendment to the Constitution of the United States relating to contributions and expenditures with respect to elections.</title>
  </titles>
  <sponsor thomas_id="01504"/>
  <cosponsors>
    <cosponsor thomas_id="01740" joined="2013-12-12"/>
    <cosponsor thomas_id="01471" joined="2013-10-16"/>
    <cosponsor thomas_id="01564" joined="2013-01-22"/>
    <cosponsor thomas_id="02055" joined="2013-01-22"/>
    <cosponsor thomas_id="02196" joined="2014-02-05"/>
    <cosponsor thomas_id="01878" joined="2013-01-22"/>
    <cosponsor thomas_id="00229" joined="2013-05-20"/>
    <cosponsor thomas_id="00279" joined="2013-01-22"/>
    <cosponsor thomas_id="01857" joined="2014-06-09"/>
    <cosponsor thomas_id="01973" joined="2014-05-01"/>
    <cosponsor thomas_id="01708" joined="2013-03-13"/>
    <cosponsor thomas_id="02010" joined="2013-08-01"/>
    <cosponsor thomas_id="02170" joined="2014-07-09"/>
    <cosponsor thomas_id="01580" joined="2013-01-22"/>
    <cosponsor thomas_id="02172" joined="2013-02-04"/>
    <cosponsor thomas_id="01668" joined="2013-01-22"/>
    <cosponsor thomas_id="00701" joined="2014-06-24"/>
    <cosponsor thomas_id="01939" joined="2013-07-17"/>
    <cosponsor thomas_id="01686" joined="2013-02-27"/>
    <cosponsor thomas_id="00729" joined="2014-06-18"/>
    <cosponsor thomas_id="00735" joined="2013-02-06"/>
    <cosponsor thomas_id="00766" joined="2013-02-04"/>
    <cosponsor thomas_id="01730" joined="2013-01-22"/>
    <cosponsor thomas_id="00854" joined="2013-04-11"/>
    <cosponsor thomas_id="00868" joined="2013-03-19"/>
    <cosponsor thomas_id="02162" joined="2014-04-07"/>
    <cosponsor thomas_id="01927" joined="2013-01-22"/>
    <cosponsor thomas_id="02171" joined="2014-04-29"/>
    <cosponsor thomas_id="01756" joined="2013-02-27"/>
    <cosponsor thomas_id="01854" joined="2013-02-15"/>
    <cosponsor thomas_id="01588" joined="2014-05-01"/>
    <cosponsor thomas_id="01861" joined="2013-01-22"/>
    <cosponsor thomas_id="01818" joined="2014-05-19"/>
    <cosponsor thomas_id="01890" joined="2014-05-08"/>
    <cosponsor thomas_id="01535" joined="2013-02-26"/>
    <cosponsor thomas_id="01940" joined="2014-05-29"/>
    <cosponsor thomas_id="01209" joined="2014-05-06"/>
  </cosponsors>
  <actions>
    <action datetime="2013-01-22" state="REFERRED">
      <text>Referred to the House Committee on the Judiciary.</text>
    </action>
    <action datetime="2013-04-08">
      <text>Referred to the Subcommittee on the Constitution And Civil Justice.</text>
    </action>
  </actions>
  <committees>
    <committee subcommittee="" code="HSJU" name="House Judiciary" activity="Referral, In Committee"/>
    <committee subcommittee="Constitution and Civil Justice" code="HSJU10" name="House Judiciary" activity="Referral"/>
  </committees>
  <relatedbills>
    <bill type="sj" session="113" relation="unknown" number="19"/>
  </relatedbills>
  <subjects>
    <term name="Government operations and politics"/>
    <term name="Constitution and constitutional amendments"/>
    <term name="Elections, voting, political campaign regulation"/>
    <term name="State and local government operations"/>
  </subjects>
  <amendments/>
  <summary>1/22/2013--Introduced.
Constitutional Amendment - Grants Congress and the states the power to regulate the raising and spending of money and in-kind equivalents with respect to federal and state elections, respectively.</summary>
</bill>
