{
  "actions": [
    {
      "acted_at": "2014-05-29T16:26:00-04:00", 
      "references": [
        {
          "reference": "CR H4953-4954", 
          "type": "consideration"
        }, 
        {
          "reference": "CR H4953", 
          "type": "text"
        }
      ], 
      "text": "Amendment (A043) offered by Mr. Broun (GA).", 
      "type": "action"
    }, 
    {
      "acted_at": "2014-05-29T16:37:00-04:00", 
      "how": "by voice vote", 
      "references": [], 
      "result": "fail", 
      "text": "On agreeing to the Broun (GA) amendment (A043) Failed by voice vote.", 
      "type": "vote", 
      "vote_type": "vote", 
      "where": "h"
    }
  ], 
  "amendment_id": "hamdt732-113", 
  "amendment_type": "hamdt", 
  "amends_amendment": null, 
  "amends_bill": {
    "bill_id": "hr4660-113", 
    "bill_type": "hr", 
    "congress": 113, 
    "number": 4660
  }, 
  "amends_treaty": null, 
  "chamber": "h", 
  "congress": "113", 
  "description": "Amendment sought to reduce funding for the Office of Science and Technology Policy account by $1 million and to apply the savings to the spending reduction account.", 
  "house_number": 43, 
  "introduced_at": "2014-05-29", 
  "number": 732, 
  "purpose": "An amendment to reduce funding for the OSTP account by $1,000,000 and apply the savings to the spending reduction account.", 
  "sponsor": {
    "district": "10", 
    "name": "Broun, Paul C.", 
    "state": "GA", 
    "thomas_id": "01882", 
    "title": "Rep", 
    "type": "person"
  }, 
  "status": "fail", 
  "status_at": "2014-05-29T16:37:00-04:00", 
  "updated_at": "2014-08-14T13:37:38-04:00"
}