<bill session="113" type="h" number="4461" updated="2014-08-18T01:17:19-04:00">
  <state datetime="2014-04-10">REFERRED</state>
  <status>
    <introduced datetime="2014-04-10"/>
  </status>
  <introduced datetime="2014-04-10"/>
  <titles>
    <title type="short" as="introduced">Climate Change Education Act</title>
    <title type="official" as="introduced">To authorize the National Oceanic and Atmospheric Administration to establish a Climate Change Education Program.</title>
  </titles>
  <sponsor thomas_id="01634"/>
  <cosponsors>
    <cosponsor thomas_id="02159" joined="2014-05-08"/>
    <cosponsor thomas_id="01474" joined="2014-05-08"/>
    <cosponsor thomas_id="02196" joined="2014-06-25"/>
    <cosponsor thomas_id="01708" joined="2014-05-08"/>
    <cosponsor thomas_id="01580" joined="2014-05-08"/>
    <cosponsor thomas_id="02101" joined="2014-05-08"/>
    <cosponsor thomas_id="01501" joined="2014-05-08"/>
    <cosponsor thomas_id="02111" joined="2014-05-08"/>
    <cosponsor thomas_id="01504" joined="2014-05-08"/>
    <cosponsor thomas_id="01832" joined="2014-05-08"/>
    <cosponsor thomas_id="00850" joined="2014-05-08"/>
    <cosponsor thomas_id="00868" joined="2014-05-08"/>
    <cosponsor thomas_id="02004" joined="2014-05-08"/>
  </cosponsors>
  <actions>
    <action datetime="2014-04-10" state="REFERRED">
      <text>Referred to the Committee on Energy and Commerce, and in addition to the Committee on Education and the Workforce, for a period to be subsequently determined by the Speaker, in each case for consideration of such provisions as fall within the jurisdiction of the committee concerned.</text>
    </action>
    <action datetime="2014-04-10">
      <text>Referred to House Energy and Commerce</text>
    </action>
    <action datetime="2014-04-10">
      <text>Referred to House Education and the Workforce</text>
    </action>
    <action datetime="2014-04-11">
      <text>Referred to the Subcommittee on Energy and Power.</text>
    </action>
    <action datetime="2014-04-28">
      <text>Sponsor introductory remarks on measure.</text>
      <reference ref="CR H3223"/>
    </action>
    <action datetime="2014-06-13">
      <text>Referred to the Subcommittee on Early Childhood, Elementary, and Secondary Education.</text>
    </action>
    <action datetime="2014-06-13">
      <text>Referred to the Subcommittee on Higher Education and Workforce Training.</text>
    </action>
  </actions>
  <committees>
    <committee subcommittee="" code="HSIF" name="House Energy and Commerce" activity="Referral"/>
    <committee subcommittee="Energy and Power" code="HSIF03" name="House Energy and Commerce" activity="Referral"/>
    <committee subcommittee="" code="HSED" name="House Education and the Workforce" activity="Referral"/>
    <committee subcommittee="Early Childhood, Elementary, and Secondary Education" code="HSED14" name="House Education and the Workforce" activity="Referral"/>
    <committee subcommittee="Higher Education and Workforce Training" code="HSED13" name="House Education and the Workforce" activity="Referral"/>
  </committees>
  <relatedbills/>
  <subjects>
    <term name="Environmental protection"/>
    <term name="Advanced technology and technological innovations"/>
    <term name="Air quality"/>
    <term name="Alternative and renewable resources"/>
    <term name="Climate change and greenhouse gases"/>
    <term name="Education programs funding"/>
    <term name="Educational facilities and institutions"/>
    <term name="Elementary and secondary education"/>
    <term name="Employment and training programs"/>
    <term name="Energy efficiency and conservation"/>
    <term name="Environmental health"/>
    <term name="Environmental technology"/>
    <term name="Government information and archives"/>
    <term name="Higher education"/>
    <term name="Teaching, teachers, curricula"/>
    <term name="Vocational education"/>
  </subjects>
  <amendments/>
</bill>
