<bill session="113" type="h" number="2255" updated="2014-08-18T00:00:31-04:00">
  <state datetime="2013-06-04">REFERRED</state>
  <status>
    <introduced datetime="2013-06-04"/>
  </status>
  <introduced datetime="2013-06-04"/>
  <titles>
    <title type="official" as="introduced">To amend the Chesapeake and Ohio Canal Development Act to extend to the Chesapeake and Ohio Canal National Historical Park Commission.</title>
  </titles>
  <sponsor thomas_id="01729"/>
  <cosponsors>
    <cosponsor thomas_id="01959" joined="2013-06-12"/>
    <cosponsor thomas_id="02133" joined="2013-06-04"/>
    <cosponsor thomas_id="00832" joined="2013-07-31"/>
    <cosponsor thomas_id="01238" joined="2013-06-04"/>
  </cosponsors>
  <actions>
    <action datetime="2013-06-04" state="REFERRED">
      <text>Referred to the House Committee on Natural Resources.</text>
    </action>
    <action datetime="2013-06-10">
      <text>Referred to the Subcommittee on Public Lands and Environmental Regulation.</text>
    </action>
  </actions>
  <committees>
    <committee subcommittee="" code="HSII" name="House Natural Resources" activity="Referral"/>
    <committee subcommittee="Public Lands and Environmental Regulation" code="HSII10" name="House Natural Resources" activity="Referral"/>
  </committees>
  <relatedbills>
    <bill type="s" session="113" relation="unknown" number="476"/>
  </relatedbills>
  <subjects>
    <term name="Public lands and natural resources"/>
    <term name="Advisory bodies"/>
    <term name="Dams and canals"/>
    <term name="District of Columbia"/>
    <term name="Historic sites and heritage areas"/>
    <term name="Maryland"/>
    <term name="Parks, recreation areas, trails"/>
    <term name="West Virginia"/>
  </subjects>
  <amendments/>
  <summary>6/4/2013--Introduced.
Amends the Chesapeake and Ohio Canal Development Act to extend the Chesapeake and Ohio Canal National Historical Park Commission until 10 years after the enactment of this Act.</summary>
</bill>
