{
  "actions": [
    {
      "acted_at": "2014-07-15", 
      "committees": [
        "HSJU"
      ], 
      "references": [], 
      "status": "REFERRED", 
      "text": "Referred to the Committee on the Judiciary, and in addition to the Committees on Foreign Affairs, Homeland Security, Armed Services, and Ways and Means, for a period to be subsequently determined by the Speaker, in each case for consideration of such provisions as fall within the jurisdiction of the committee concerned.", 
      "type": "referral"
    }, 
    {
      "acted_at": "2014-07-15", 
      "committees": [
        "HSJU"
      ], 
      "references": [], 
      "text": "Referred to House Judiciary", 
      "type": "referral"
    }, 
    {
      "acted_at": "2014-07-15", 
      "committees": [
        "HSFA"
      ], 
      "references": [], 
      "text": "Referred to House Foreign Affairs", 
      "type": "referral"
    }, 
    {
      "acted_at": "2014-07-15", 
      "committees": [
        "HSHM"
      ], 
      "references": [], 
      "text": "Referred to House Homeland Security", 
      "type": "referral"
    }, 
    {
      "acted_at": "2014-07-15", 
      "committees": [
        "HSAS"
      ], 
      "references": [], 
      "text": "Referred to House Armed Services", 
      "type": "referral"
    }, 
    {
      "acted_at": "2014-07-15", 
      "committees": [
        "HSWM"
      ], 
      "references": [], 
      "text": "Referred to House Ways and Means", 
      "type": "referral"
    }, 
    {
      "acted_at": "2014-07-23", 
      "in_committee": null, 
      "references": [], 
      "text": "Referred to the Subcommittee on Border and Maritime Security.", 
      "type": "referral"
    }
  ], 
  "amendments": [], 
  "bill_id": "hr5114-113", 
  "bill_type": "hr", 
  "by_request": false, 
  "committees": [
    {
      "activity": [
        "referral"
      ], 
      "committee": "House Judiciary", 
      "committee_id": "HSJU"
    }, 
    {
      "activity": [
        "referral"
      ], 
      "committee": "House Foreign Affairs", 
      "committee_id": "HSFA"
    }, 
    {
      "activity": [
        "referral"
      ], 
      "committee": "House Homeland Security", 
      "committee_id": "HSHM"
    }, 
    {
      "activity": [
        "referral"
      ], 
      "committee": "House Homeland Security", 
      "committee_id": "HSHM", 
      "subcommittee": "Subcommittee on Border and Maritime Security", 
      "subcommittee_id": "11"
    }, 
    {
      "activity": [
        "referral"
      ], 
      "committee": "House Armed Services", 
      "committee_id": "HSAS"
    }, 
    {
      "activity": [
        "referral"
      ], 
      "committee": "House Ways and Means", 
      "committee_id": "HSWM"
    }
  ], 
  "congress": "113", 
  "cosponsors": [
    {
      "district": "2", 
      "name": "Barber, Ron", 
      "sponsored_at": "2014-07-15", 
      "state": "AZ", 
      "thomas_id": "02093", 
      "title": "Rep", 
      "withdrawn_at": null
    }, 
    {
      "district": "11", 
      "name": "Conaway, K. Michael", 
      "sponsored_at": "2014-07-25", 
      "state": "TX", 
      "thomas_id": "01805", 
      "title": "Rep", 
      "withdrawn_at": null
    }, 
    {
      "district": "15", 
      "name": "Dent, Charles W.", 
      "sponsored_at": "2014-07-17", 
      "state": "PA", 
      "thomas_id": "01799", 
      "title": "Rep", 
      "withdrawn_at": null
    }, 
    {
      "district": "27", 
      "name": "Farenthold, Blake", 
      "sponsored_at": "2014-07-15", 
      "state": "TX", 
      "thomas_id": "02067", 
      "title": "Rep", 
      "withdrawn_at": null
    }, 
    {
      "district": "4", 
      "name": "Hall, Ralph M.", 
      "sponsored_at": "2014-07-28", 
      "state": "TX", 
      "thomas_id": "00484", 
      "title": "Rep", 
      "withdrawn_at": null
    }, 
    {
      "district": "3", 
      "name": "Lipinski, Daniel", 
      "sponsored_at": "2014-08-01", 
      "state": "IL", 
      "thomas_id": "01781", 
      "title": "Rep", 
      "withdrawn_at": null
    }, 
    {
      "district": "24", 
      "name": "Marchant, Kenny", 
      "sponsored_at": "2014-07-25", 
      "state": "TX", 
      "thomas_id": "01806", 
      "title": "Rep", 
      "withdrawn_at": null
    }, 
    {
      "district": "10", 
      "name": "McCaul, Michael T.", 
      "sponsored_at": "2014-07-22", 
      "state": "TX", 
      "thomas_id": "01804", 
      "title": "Rep", 
      "withdrawn_at": null
    }, 
    {
      "district": "7", 
      "name": "Peterson, Collin C.", 
      "sponsored_at": "2014-07-25", 
      "state": "MN", 
      "thomas_id": "00910", 
      "title": "Rep", 
      "withdrawn_at": null
    }
  ], 
  "enacted_as": null, 
  "history": {
    "active": false, 
    "awaiting_signature": false, 
    "enacted": false, 
    "vetoed": false
  }, 
  "introduced_at": "2014-07-15", 
  "number": "5114", 
  "official_title": "To facilitate the expedited processing of minors entering the United States across the southern border and for other purposes.", 
  "popular_title": null, 
  "related_bills": [
    {
      "bill_id": "s2666-113", 
      "reason": "related", 
      "type": "bill"
    }
  ], 
  "short_title": "Helping Unaccompanied Minors and Alleviating National Emergency Act", 
  "sponsor": {
    "district": "28", 
    "name": "Cuellar, Henry", 
    "state": "TX", 
    "thomas_id": "01807", 
    "title": "Rep", 
    "type": "person"
  }, 
  "status": "REFERRED", 
  "status_at": "2014-07-15", 
  "subjects": [], 
  "subjects_top_term": null, 
  "summary": null, 
  "titles": [
    {
      "as": "introduced", 
      "is_for_portion": false, 
      "title": "Helping Unaccompanied Minors and Alleviating National Emergency Act", 
      "type": "short"
    }, 
    {
      "as": "introduced", 
      "is_for_portion": false, 
      "title": "HUMANE Act", 
      "type": "short"
    }, 
    {
      "as": "introduced", 
      "is_for_portion": false, 
      "title": "To facilitate the expedited processing of minors entering the United States across the southern border and for other purposes.", 
      "type": "official"
    }
  ], 
  "updated_at": "2014-08-18T01:39:41-04:00"
}