{
  "actions": [
    {
      "acted_at": "2014-03-25", 
      "committees": [
        "HSIF"
      ], 
      "references": [], 
      "status": "REFERRED", 
      "text": "Referred to the House Committee on Energy and Commerce.", 
      "type": "referral"
    }, 
    {
      "acted_at": "2014-03-28", 
      "in_committee": null, 
      "references": [], 
      "text": "Referred to the Subcommittee on Health.", 
      "type": "referral"
    }, 
    {
      "acted_at": "2014-06-19", 
      "in_committee": null, 
      "in_subcommittee": null, 
      "references": [], 
      "text": "Subcommittee Consideration and Mark-up Session Held.", 
      "type": "action"
    }, 
    {
      "acted_at": "2014-06-19", 
      "in_committee": null, 
      "in_subcommittee": null, 
      "references": [], 
      "text": "Forwarded by Subcommittee to Full Committee (Amended) by Unanimous Consent .", 
      "type": "action"
    }, 
    {
      "acted_at": "2014-07-14", 
      "in_committee": null, 
      "references": [], 
      "text": "Committee Consideration and Mark-up Session Held.", 
      "type": "action"
    }, 
    {
      "acted_at": "2014-07-15", 
      "in_committee": null, 
      "references": [], 
      "text": "Committee Consideration and Mark-up Session Held.", 
      "type": "action"
    }, 
    {
      "acted_at": "2014-07-15", 
      "in_committee": null, 
      "references": [], 
      "status": "REPORTED", 
      "text": "Ordered to be Reported (Amended) by Voice Vote.", 
      "type": "calendar"
    }, 
    {
      "acted_at": "2014-07-24T18:17:00-04:00", 
      "committees": [
        "HSIF"
      ], 
      "references": [], 
      "text": "Reported (Amended) by the Committee on Energy and Commerce. H. Rept. 113-559.", 
      "type": "action"
    }, 
    {
      "acted_at": "2014-07-24T18:17:00-04:00", 
      "calendar": "Union", 
      "number": "419", 
      "references": [], 
      "text": "Placed on the Union Calendar, Calendar No. 419.", 
      "type": "calendar", 
      "under": null
    }
  ], 
  "amendments": [], 
  "bill_id": "hr4290-113", 
  "bill_type": "hr", 
  "by_request": false, 
  "committees": [
    {
      "activity": [
        "referral", 
        "markup", 
        "reporting"
      ], 
      "committee": "House Energy and Commerce", 
      "committee_id": "HSIF"
    }, 
    {
      "activity": [
        "referral", 
        "markup", 
        "reporting"
      ], 
      "committee": "House Energy and Commerce", 
      "committee_id": "HSIF", 
      "subcommittee": "Subcommittee on Health", 
      "subcommittee_id": "14"
    }
  ], 
  "congress": "113", 
  "cosponsors": [
    {
      "district": "2", 
      "name": "Amodei, Mark E.", 
      "sponsored_at": "2014-06-11", 
      "state": "NV", 
      "thomas_id": "02090", 
      "title": "Rep", 
      "withdrawn_at": null
    }, 
    {
      "district": "2", 
      "name": "King, Peter T.", 
      "sponsored_at": "2014-03-25", 
      "state": "NY", 
      "thomas_id": "00635", 
      "title": "Rep", 
      "withdrawn_at": null
    }, 
    {
      "district": "2", 
      "name": "Loebsack, David", 
      "sponsored_at": "2014-06-11", 
      "state": "IA", 
      "thomas_id": "01846", 
      "title": "Rep", 
      "withdrawn_at": null
    }, 
    {
      "district": "2", 
      "name": "McGovern, James P.", 
      "sponsored_at": "2014-05-09", 
      "state": "MA", 
      "thomas_id": "01504", 
      "title": "Rep", 
      "withdrawn_at": null
    }, 
    {
      "district": "1", 
      "name": "Shea-Porter, Carol", 
      "sponsored_at": "2014-06-11", 
      "state": "NH", 
      "thomas_id": "01861", 
      "title": "Rep", 
      "withdrawn_at": null
    }
  ], 
  "enacted_as": null, 
  "history": {
    "active": true, 
    "active_at": "2014-06-19", 
    "awaiting_signature": false, 
    "enacted": false, 
    "vetoed": false
  }, 
  "introduced_at": "2014-03-25", 
  "number": "4290", 
  "official_title": "To amend the Public Health Service Act to reauthorize the Emergency Medical Services for Children Program.", 
  "popular_title": null, 
  "related_bills": [
    {
      "bill_id": "s2154-113", 
      "reason": "related", 
      "type": "bill"
    }
  ], 
  "short_title": "Wakefield Act of 2014", 
  "sponsor": {
    "district": "4", 
    "name": "Matheson, Jim", 
    "state": "UT", 
    "thomas_id": "01671", 
    "title": "Rep", 
    "type": "person"
  }, 
  "status": "REPORTED", 
  "status_at": "2014-07-15", 
  "subjects": [
    "Child health", 
    "Emergency medical services and trauma care", 
    "Health", 
    "Health programs administration and funding"
  ], 
  "subjects_top_term": "Health", 
  "summary": {
    "as": "Reported to House amended", 
    "date": "2014-07-24", 
    "text": "Wakefield Act of 2014 - Amends the Public Health Service Act to extend the authorization of appropriations for the Emergency Medical Services for Children Program through FY2019."
  }, 
  "titles": [
    {
      "as": "introduced", 
      "is_for_portion": false, 
      "title": "Wakefield Act of 2014", 
      "type": "short"
    }, 
    {
      "as": "reported to house", 
      "is_for_portion": false, 
      "title": "Wakefield Act of 2014", 
      "type": "short"
    }, 
    {
      "as": "introduced", 
      "is_for_portion": false, 
      "title": "To amend the Public Health Service Act to reauthorize the Emergency Medical Services for Children Program.", 
      "type": "official"
    }
  ], 
  "updated_at": "2014-08-14T13:28:00-04:00"
}