{
  "actions": [
    {
      "acted_at": "2014-06-09T23:09:00-04:00", 
      "references": [
        {
          "reference": "CR H5183-5184", 
          "type": "consideration"
        }, 
        {
          "reference": "CR H5183", 
          "type": "text"
        }
      ], 
      "text": "Amendment (A043) offered by Mr. Grayson.", 
      "type": "action"
    }, 
    {
      "acted_at": "2014-06-09T23:12:00-04:00", 
      "references": [], 
      "text": "Mr. Latham raised a point of order against the Grayson amendment (A043). Mr. Latham stated that the Grayson amendment sought to change existing law and constituted legislation in an appropriations bill. The Chair sustained the point of order.", 
      "type": "action"
    }
  ], 
  "amendment_id": "hamdt820-113", 
  "amendment_type": "hamdt", 
  "amends_amendment": null, 
  "amends_bill": {
    "bill_id": "hr4745-113", 
    "bill_type": "hr", 
    "congress": 113, 
    "number": 4745
  }, 
  "amends_treaty": null, 
  "chamber": "h", 
  "congress": "113", 
  "description": null, 
  "house_number": 43, 
  "introduced_at": "2014-06-09", 
  "number": 820, 
  "purpose": "An amendment to prohibit use of funds to provide a per-passenger subsidy in excess of $250 under the Essential Air Service program.", 
  "sponsor": {
    "district": "9", 
    "name": "Grayson, Alan", 
    "state": "FL", 
    "thomas_id": "01914", 
    "title": "Rep", 
    "type": "person"
  }, 
  "status": "offered", 
  "status_at": "2014-06-09", 
  "updated_at": "2014-08-14T13:38:23-04:00"
}