<bill session="113" type="h" number="5086" updated="2014-08-14T13:34:53-04:00">
  <state datetime="2014-07-11">REFERRED</state>
  <status>
    <introduced datetime="2014-07-11"/>
  </status>
  <introduced datetime="2014-07-11"/>
  <titles>
    <title type="official" as="introduced">To amend the National Trails System Act to direct the Secretary of the Interior to conduct a study on the feasibility of designating the Chief Standing Bear National Historic Trail, and for other purposes.</title>
  </titles>
  <sponsor thomas_id="01793"/>
  <cosponsors>
    <cosponsor thomas_id="01742" joined="2014-07-25"/>
  </cosponsors>
  <actions>
    <action datetime="2014-07-11" state="REFERRED">
      <text>Referred to the House Committee on Natural Resources.</text>
    </action>
    <action datetime="2014-07-21">
      <text>Referred to the Subcommittee on Public Lands and Environmental Regulation.</text>
    </action>
    <action datetime="2014-07-29">
      <text>Subcommittee Hearings Held.</text>
    </action>
  </actions>
  <committees>
    <committee subcommittee="" code="HSII" name="House Natural Resources" activity="Referral"/>
    <committee subcommittee="Public Lands and Environmental Regulation" code="HSII10" name="House Natural Resources" activity="Referral, Hearings"/>
  </committees>
  <relatedbills/>
  <subjects/>
  <amendments/>
</bill>
